{
  "logged_in" : {
    "36d09310-c225-4120-8612-4044c3d93ea5" : {
      "age" : {
        "age" : 37,
        "day" : "3",
        "month" : "4",
        "year" : "1979"
      },
      "chat" : false,
      "chatlog" : false,
      "chatsearch" : false,
      "content" : {
        "games" : {
          "batmanarkhamknight" : {
            "chats" : 0,
            "intrest" : 0,
            "name" : "Batman Arkham Knight",
            "uid" : "085557-656-325-8b4-3d9b1c573"
          },
          "bloodborne" : {
            "chats" : 0,
            "intrest" : 0,
            "name" : "Blood Borne",
            "uid" : "541a54-037-a90-44f-c55353bf6"
          },
          "fallout4" : {
            "chats" : 0,
            "intrest" : 0,
            "name" : "Fallout 4",
            "uid" : "d7567e-46a-26e-537-8215e1735"
          },
          "watchdogs" : {
            "chats" : 0,
            "intrest" : 0,
            "name" : "Watch Dogs",
            "uid" : "96d33b-598-891-6ba-35212c097"
          }
        },
        "tv_shows" : {
          "americanhorrorstory" : {
            "chats" : 0,
            "intrest" : 0,
            "name" : "American Horror Story",
            "uid" : "b2ba4f-6f7-bed-aaa-59571eb75"
          },
          "arrow" : {
            "chats" : 0,
            "intrest" : 0,
            "name" : "Arrow",
            "uid" : "3ca510-df6-f9e-e24-a73b21ecd"
          },
          "bojackhorseman" : {
            "chats" : 0,
            "intrest" : 0,
            "name" : "Bojack Horseman",
            "uid" : "bcab14-ca1-18c-ea4-356496c3a"
          },
          "daredevil" : {
            "chats" : 0,
            "intrest" : 0,
            "name" : "Dare Devil",
            "uid" : "29fe21-d00-917-f43-d4e0cf5e9"
          },
          "gameofthrones" : {
            "chats" : 0,
            "intrest" : 0,
            "name" : "Game Of Thrones",
            "uid" : "e1d437-d00-117-ccc-210017dfa"
          },
          "houseofcards" : {
            "chats" : 0,
            "intrest" : 0,
            "name" : "House Of Cards",
            "uid" : "0f8612-0a0-73d-5e6-a0363eb34"
          },
          "narcos" : {
            "chats" : 0,
            "intrest" : 0,
            "name" : "Narcos",
            "uid" : "9a08bf-434-737-6ef-1e0e1dad1"
          },
          "orangeisthenewblack" : {
            "chats" : 0,
            "intrest" : 0,
            "name" : "Orange Is The New Black",
            "uid" : "1faf28-417-83f-765-ff3c21090"
          },
          "scream" : {
            "chats" : 0,
            "intrest" : 0,
            "name" : "Scream",
            "uid" : "87bc8c-f90-d85-c44-daf143df8"
          },
          "suits" : {
            "chats" : 0,
            "intrest" : 0,
            "name" : "Suits",
            "uid" : "ca953d-919-401-7e9-a2b44410f"
          },
          "supernatural" : {
            "chats" : 0,
            "intrest" : 0,
            "name" : "Super Natural",
            "uid" : "7291d0-645-9f4-446-d2464973e"
          },
          "thewalkingdead" : {
            "chats" : 0,
            "intrest" : 0,
            "name" : "The Walking Dead",
            "uid" : "0cb6a4-5e5-b63-f4e-c7fb3b75f"
          },
          "truedetective" : {
            "chats" : 0,
            "intrest" : 0,
            "name" : "True Detective",
            "uid" : "749767-585-561-5fb-64b93cda3"
          }
        }
      },
      "date" : "13/1/2016 ( 23:2:5:162 ) ",
      "email" : "mama@gmail.com",
      "facebook_auth" : false,
      "google_auth" : false,
      "ip_address" : "70.27.105.227",
      "logged_in" : true,
      "name" : "jaden banson",
      "onefan_auth" : true,
      "password" : "1234",
      "personal_look" : false,
      "udid" : "36d09310-c225-4120-8612-4044c3d93ea5",
      "username" : "snow_outside89"
    },
    "46e0a364-71c8-4757-9c44-967b4e6f5886" : {
      "age" : {
        "age" : 25,
        "day" : "7",
        "month" : "2",
        "year" : "1991"
      },
      "chat" : false,
      "chatlog" : false,
      "chatsearch" : false,
      "content" : {
        "games" : {
          "batmanarkhamknight" : {
            "chats" : 0,
            "intrest" : 0,
            "name" : "Batman Arkham Knight",
            "uid" : "085557-656-325-8b4-3d9b1c573"
          },
          "bloodborne" : {
            "chats" : 0,
            "intrest" : 0,
            "name" : "Blood Borne",
            "uid" : "541a54-037-a90-44f-c55353bf6"
          },
          "fallout4" : {
            "chats" : 0,
            "intrest" : 0,
            "name" : "Fallout 4",
            "uid" : "d7567e-46a-26e-537-8215e1735"
          },
          "watchdogs" : {
            "chats" : 0,
            "intrest" : 0,
            "name" : "Watch Dogs",
            "uid" : "96d33b-598-891-6ba-35212c097"
          }
        },
        "tv_shows" : {
          "americanhorrorstory" : {
            "chats" : 0,
            "intrest" : 0,
            "name" : "American Horror Story",
            "uid" : "b2ba4f-6f7-bed-aaa-59571eb75"
          },
          "arrow" : {
            "chats" : 0,
            "intrest" : 0,
            "name" : "Arrow",
            "uid" : "3ca510-df6-f9e-e24-a73b21ecd"
          },
          "bojackhorseman" : {
            "chats" : 0,
            "intrest" : 0,
            "name" : "Bojack Horseman",
            "uid" : "bcab14-ca1-18c-ea4-356496c3a"
          },
          "daredevil" : {
            "chats" : 0,
            "intrest" : 0,
            "name" : "Dare Devil",
            "uid" : "29fe21-d00-917-f43-d4e0cf5e9"
          },
          "gameofthrones" : {
            "chats" : 0,
            "intrest" : 0,
            "name" : "Game Of Thrones",
            "uid" : "e1d437-d00-117-ccc-210017dfa"
          },
          "houseofcards" : {
            "chats" : 0,
            "intrest" : 0,
            "name" : "House Of Cards",
            "uid" : "0f8612-0a0-73d-5e6-a0363eb34"
          },
          "narcos" : {
            "chats" : 0,
            "intrest" : 0,
            "name" : "Narcos",
            "uid" : "9a08bf-434-737-6ef-1e0e1dad1"
          },
          "orangeisthenewblack" : {
            "chats" : 0,
            "intrest" : 0,
            "name" : "Orange Is The New Black",
            "uid" : "1faf28-417-83f-765-ff3c21090"
          },
          "scream" : {
            "chats" : 0,
            "intrest" : 0,
            "name" : "Scream",
            "uid" : "87bc8c-f90-d85-c44-daf143df8"
          },
          "suits" : {
            "chats" : 0,
            "intrest" : 0,
            "name" : "Suits",
            "uid" : "ca953d-919-401-7e9-a2b44410f"
          },
          "supernatural" : {
            "chats" : 0,
            "intrest" : 0,
            "name" : "Super Natural",
            "uid" : "7291d0-645-9f4-446-d2464973e"
          },
          "thewalkingdead" : {
            "chats" : 0,
            "intrest" : 0,
            "name" : "The Walking Dead",
            "uid" : "0cb6a4-5e5-b63-f4e-c7fb3b75f"
          },
          "truedetective" : {
            "chats" : 0,
            "intrest" : 0,
            "name" : "True Detective",
            "uid" : "749767-585-561-5fb-64b93cda3"
          }
        }
      },
      "date" : "13/1/2016 ( 21:57:17:57 ) ",
      "email" : "future@gmail.com",
      "facebook_auth" : false,
      "google_auth" : false,
      "ip_address" : "70.27.105.227",
      "logged_in" : true,
      "name" : "jaden banson",
      "onefan_auth" : true,
      "password" : "1234",
      "personal_look" : false,
      "udid" : "46e0a364-71c8-4757-9c44-967b4e6f5886",
      "username" : "future_iscnool"
    }
  },
  "logged_user_count" : {
    "usercount" : 2
  },
  "totalusers" : {
    "users" : 5
  },
  "users" : {
    "36d09310-c225-4120-8612-4044c3d93ea5" : {
      "age" : {
        "age" : 37,
        "day" : "3",
        "month" : "4",
        "year" : "1979"
      },
      "chat" : false,
      "chatlog" : false,
      "chatsearch" : false,
      "content" : {
        "games" : {
          "batmanarkhamknight" : {
            "chats" : 0,
            "intrest" : 0,
            "name" : "Batman Arkham Knight",
            "uid" : "085557-656-325-8b4-3d9b1c573"
          },
          "bloodborne" : {
            "chats" : 0,
            "intrest" : 0,
            "name" : "Blood Borne",
            "uid" : "541a54-037-a90-44f-c55353bf6"
          },
          "fallout4" : {
            "chats" : 0,
            "intrest" : 0,
            "name" : "Fallout 4",
            "uid" : "d7567e-46a-26e-537-8215e1735"
          },
          "watchdogs" : {
            "chats" : 0,
            "intrest" : 0,
            "name" : "Watch Dogs",
            "uid" : "96d33b-598-891-6ba-35212c097"
          }
        },
        "tv_shows" : {
          "americanhorrorstory" : {
            "chats" : 0,
            "intrest" : 0,
            "name" : "American Horror Story",
            "uid" : "b2ba4f-6f7-bed-aaa-59571eb75"
          },
          "arrow" : {
            "chats" : 0,
            "intrest" : 0,
            "name" : "Arrow",
            "uid" : "3ca510-df6-f9e-e24-a73b21ecd"
          },
          "bojackhorseman" : {
            "chats" : 0,
            "intrest" : 0,
            "name" : "Bojack Horseman",
            "uid" : "bcab14-ca1-18c-ea4-356496c3a"
          },
          "daredevil" : {
            "chats" : 0,
            "intrest" : 0,
            "name" : "Dare Devil",
            "uid" : "29fe21-d00-917-f43-d4e0cf5e9"
          },
          "gameofthrones" : {
            "chats" : 0,
            "intrest" : 0,
            "name" : "Game Of Thrones",
            "uid" : "e1d437-d00-117-ccc-210017dfa"
          },
          "houseofcards" : {
            "chats" : 0,
            "intrest" : 0,
            "name" : "House Of Cards",
            "uid" : "0f8612-0a0-73d-5e6-a0363eb34"
          },
          "narcos" : {
            "chats" : 0,
            "intrest" : 0,
            "name" : "Narcos",
            "uid" : "9a08bf-434-737-6ef-1e0e1dad1"
          },
          "orangeisthenewblack" : {
            "chats" : 0,
            "intrest" : 0,
            "name" : "Orange Is The New Black",
            "uid" : "1faf28-417-83f-765-ff3c21090"
          },
          "scream" : {
            "chats" : 0,
            "intrest" : 0,
            "name" : "Scream",
            "uid" : "87bc8c-f90-d85-c44-daf143df8"
          },
          "suits" : {
            "chats" : 0,
            "intrest" : 0,
            "name" : "Suits",
            "uid" : "ca953d-919-401-7e9-a2b44410f"
          },
          "supernatural" : {
            "chats" : 0,
            "intrest" : 0,
            "name" : "Super Natural",
            "uid" : "7291d0-645-9f4-446-d2464973e"
          },
          "thewalkingdead" : {
            "chats" : 0,
            "intrest" : 0,
            "name" : "The Walking Dead",
            "uid" : "0cb6a4-5e5-b63-f4e-c7fb3b75f"
          },
          "truedetective" : {
            "chats" : 0,
            "intrest" : 0,
            "name" : "True Detective",
            "uid" : "749767-585-561-5fb-64b93cda3"
          }
        }
      },
      "date" : "13/1/2016 ( 23:2:5:162 ) ",
      "email" : "mama@gmail.com",
      "facebook_auth" : false,
      "google_auth" : false,
      "ip_address" : "70.27.105.227",
      "logged_in" : true,
      "name" : "jaden banson",
      "onefan_auth" : true,
      "password" : "1234",
      "personal_look" : false,
      "udid" : "36d09310-c225-4120-8612-4044c3d93ea5",
      "username" : "snow_outside89"
    },
    "46e0a364-71c8-4757-9c44-967b4e6f5886" : {
      "age" : {
        "age" : 25,
        "day" : "7",
        "month" : "2",
        "year" : "1991"
      },
      "chat" : false,
      "chatlog" : false,
      "chatsearch" : false,
      "content" : {
        "games" : {
          "batmanarkhamknight" : {
            "chats" : 0,
            "intrest" : 0,
            "name" : "Batman Arkham Knight",
            "uid" : "085557-656-325-8b4-3d9b1c573"
          },
          "bloodborne" : {
            "chats" : 0,
            "intrest" : 0,
            "name" : "Blood Borne",
            "uid" : "541a54-037-a90-44f-c55353bf6"
          },
          "fallout4" : {
            "chats" : 0,
            "intrest" : 0,
            "name" : "Fallout 4",
            "uid" : "d7567e-46a-26e-537-8215e1735"
          },
          "watchdogs" : {
            "chats" : 0,
            "intrest" : 0,
            "name" : "Watch Dogs",
            "uid" : "96d33b-598-891-6ba-35212c097"
          }
        },
        "tv_shows" : {
          "americanhorrorstory" : {
            "chats" : 0,
            "intrest" : 0,
            "name" : "American Horror Story",
            "uid" : "b2ba4f-6f7-bed-aaa-59571eb75"
          },
          "arrow" : {
            "chats" : 0,
            "intrest" : 0,
            "name" : "Arrow",
            "uid" : "3ca510-df6-f9e-e24-a73b21ecd"
          },
          "bojackhorseman" : {
            "chats" : 0,
            "intrest" : 0,
            "name" : "Bojack Horseman",
            "uid" : "bcab14-ca1-18c-ea4-356496c3a"
          },
          "daredevil" : {
            "chats" : 0,
            "intrest" : 0,
            "name" : "Dare Devil",
            "uid" : "29fe21-d00-917-f43-d4e0cf5e9"
          },
          "gameofthrones" : {
            "chats" : 0,
            "intrest" : 0,
            "name" : "Game Of Thrones",
            "uid" : "e1d437-d00-117-ccc-210017dfa"
          },
          "houseofcards" : {
            "chats" : 0,
            "intrest" : 0,
            "name" : "House Of Cards",
            "uid" : "0f8612-0a0-73d-5e6-a0363eb34"
          },
          "narcos" : {
            "chats" : 0,
            "intrest" : 0,
            "name" : "Narcos",
            "uid" : "9a08bf-434-737-6ef-1e0e1dad1"
          },
          "orangeisthenewblack" : {
            "chats" : 0,
            "intrest" : 0,
            "name" : "Orange Is The New Black",
            "uid" : "1faf28-417-83f-765-ff3c21090"
          },
          "scream" : {
            "chats" : 0,
            "intrest" : 0,
            "name" : "Scream",
            "uid" : "87bc8c-f90-d85-c44-daf143df8"
          },
          "suits" : {
            "chats" : 0,
            "intrest" : 0,
            "name" : "Suits",
            "uid" : "ca953d-919-401-7e9-a2b44410f"
          },
          "supernatural" : {
            "chats" : 0,
            "intrest" : 0,
            "name" : "Super Natural",
            "uid" : "7291d0-645-9f4-446-d2464973e"
          },
          "thewalkingdead" : {
            "chats" : 0,
            "intrest" : 0,
            "name" : "The Walking Dead",
            "uid" : "0cb6a4-5e5-b63-f4e-c7fb3b75f"
          },
          "truedetective" : {
            "chats" : 0,
            "intrest" : 0,
            "name" : "True Detective",
            "uid" : "749767-585-561-5fb-64b93cda3"
          }
        }
      },
      "date" : "13/1/2016 ( 21:57:17:57 ) ",
      "email" : "future@gmail.com",
      "facebook_auth" : false,
      "google_auth" : false,
      "ip_address" : "70.27.105.227",
      "logged_in" : true,
      "name" : "jaden banson",
      "onefan_auth" : true,
      "password" : "1234",
      "personal_look" : false,
      "udid" : "46e0a364-71c8-4757-9c44-967b4e6f5886",
      "username" : "future_iscnool"
    },
    "832a23c1-5822-43f9-93ae-2cc72a2927f1" : {
      "age" : {
        "age" : 27,
        "day" : "4",
        "month" : "3",
        "year" : "1989"
      },
      "chat" : false,
      "chatlog" : false,
      "chatsearch" : false,
      "content" : {
        "games" : {
          "085557-656-325-8b4-3d9b1c573" : {
            "intrest" : 0,
            "name" : "Batman Arkham Night"
          },
          "541a54-037-a90-44f-c55353bf6" : {
            "intrest" : 0,
            "name" : "Blood Borne"
          },
          "96d33b-598-891-6ba-35212c097" : {
            "intrest" : 0,
            "name" : "Watch Dogs"
          },
          "d7567e-46a-26e-537-8215e1735" : {
            "intrest" : 0,
            "name" : "Fallout 4"
          }
        },
        "tv_shows" : {
          "0cb6a4-5e5-b63-f4e-c7fb3b75f" : {
            "intrest" : 0,
            "name" : "The Walking Dead"
          },
          "0f8612-0a0-73d-5e6-a0363eb34" : {
            "intrest" : 0,
            "name" : "House of Cards"
          },
          "1faf28-417-83f-765-ff3c21090" : {
            "intrest" : 0,
            "name" : "Orange Is The New Black"
          },
          "29fe21-d00-917-f43-d4e0cf5e9" : {
            "intrest" : 0,
            "name" : "Daredevil"
          },
          "3ca510-df6-f9e-e24-a73b21ecd" : {
            "intrest" : 0,
            "name" : "Arrow"
          },
          "7291d0-645-9f4-446-d2464973e" : {
            "intrest" : 0,
            "name" : "Supernatural"
          },
          "749767-585-561-5fb-64b93cda3" : {
            "intrest" : 0,
            "name" : "True Detective"
          },
          "87bc8c-f90-d85-c44-daf143df8" : {
            "intrest" : 0,
            "name" : "Scream"
          },
          "9a08bf-434-737-6ef-1e0e1dad1" : {
            "intrest" : 0,
            "name" : "Narcos"
          },
          "b2ba4f-6f7-bed-aaa-59571eb75" : {
            "intrest" : 0,
            "name" : "American Horror Story"
          },
          "bcab14-ca1-18c-ea4-356496c3a" : {
            "intrest" : 0,
            "name" : "Bojack Horseman "
          },
          "ca953d-919-401-7e9-a2b44410f" : {
            "intrest" : 0,
            "name" : "Suits"
          },
          "e1d437-d00-117-ccc-210017dfa" : {
            "intrest" : 0,
            "name" : "Game of Thrones"
          }
        }
      },
      "date" : "20/1/2016 ( 21:32:6:562 ) ",
      "email" : "jaden.banson@gmail.com",
      "facebook_auth" : false,
      "google_auth" : false,
      "ip_address" : "70.26.136.82",
      "logged_in" : true,
      "name" : "Jaden Banson",
      "onefan_auth" : true,
      "password" : "playstation3",
      "personal_look" : false,
      "udid" : "832a23c1-5822-43f9-93ae-2cc72a2927f1",
      "username" : "jaden_jbi"
    },
    "d4554e6c-67f1-47bc-a923-a94c7e38b01f" : {
      "age" : {
        "age" : 25,
        "day" : "5",
        "month" : "3",
        "year" : "1991"
      },
      "chat" : false,
      "chatlog" : false,
      "chatsearch" : false,
      "content" : {
        "games" : {
          "batmanarkhamknight" : {
            "chats" : 0,
            "intrest" : 0,
            "name" : "Batman Arkham Knight",
            "uid" : "085557-656-325-8b4-3d9b1c573"
          },
          "bloodborne" : {
            "chats" : 0,
            "intrest" : 0,
            "name" : "Blood Borne",
            "uid" : "541a54-037-a90-44f-c55353bf6"
          },
          "fallout4" : {
            "chats" : 0,
            "intrest" : 0,
            "name" : "Fallout 4",
            "uid" : "d7567e-46a-26e-537-8215e1735"
          },
          "watchdogs" : {
            "chats" : 0,
            "intrest" : 0,
            "name" : "Watch Dogs",
            "uid" : "96d33b-598-891-6ba-35212c097"
          }
        },
        "tv_shows" : {
          "americanhorrorstory" : {
            "chats" : 0,
            "intrest" : 0,
            "name" : "American Horror Story",
            "uid" : "b2ba4f-6f7-bed-aaa-59571eb75"
          },
          "arrow" : {
            "chats" : 0,
            "intrest" : 0,
            "name" : "Arrow",
            "uid" : "3ca510-df6-f9e-e24-a73b21ecd"
          },
          "bojackhorseman" : {
            "chats" : 0,
            "intrest" : 0,
            "name" : "Bojack Horseman",
            "uid" : "bcab14-ca1-18c-ea4-356496c3a"
          },
          "daredevil" : {
            "chats" : 0,
            "intrest" : 0,
            "name" : "Dare Devil",
            "uid" : "29fe21-d00-917-f43-d4e0cf5e9"
          },
          "gameofthrones" : {
            "chats" : 0,
            "intrest" : 0,
            "name" : "Game Of Thrones",
            "uid" : "e1d437-d00-117-ccc-210017dfa"
          },
          "houseofcards" : {
            "chats" : 0,
            "intrest" : 0,
            "name" : "House Of Cards",
            "uid" : "0f8612-0a0-73d-5e6-a0363eb34"
          },
          "narcos" : {
            "chats" : 0,
            "intrest" : 0,
            "name" : "Narcos",
            "uid" : "9a08bf-434-737-6ef-1e0e1dad1"
          },
          "orangeisthenewblack" : {
            "chats" : 0,
            "intrest" : 0,
            "name" : "Orange Is The New Black",
            "uid" : "1faf28-417-83f-765-ff3c21090"
          },
          "scream" : {
            "chats" : 0,
            "intrest" : 0,
            "name" : "Scream",
            "uid" : "87bc8c-f90-d85-c44-daf143df8"
          },
          "suits" : {
            "chats" : 0,
            "intrest" : 0,
            "name" : "Suits",
            "uid" : "ca953d-919-401-7e9-a2b44410f"
          },
          "supernatural" : {
            "chats" : 0,
            "intrest" : 0,
            "name" : "Super Natural",
            "uid" : "7291d0-645-9f4-446-d2464973e"
          },
          "thewalkingdead" : {
            "chats" : 0,
            "intrest" : 0,
            "name" : "The Walking Dead",
            "uid" : "0cb6a4-5e5-b63-f4e-c7fb3b75f"
          },
          "truedetective" : {
            "chats" : 0,
            "intrest" : 0,
            "name" : "True Detective",
            "uid" : "749767-585-561-5fb-64b93cda3"
          }
        }
      },
      "date" : "14/1/2016 ( 15:18:17:4 ) ",
      "email" : "roads@yahoo.com",
      "facebook_auth" : false,
      "google_auth" : false,
      "ip_address" : "70.27.105.227",
      "logged_in" : false,
      "name" : "jaden banson",
      "onefan_auth" : true,
      "password" : "1234",
      "personal_look" : false,
      "udid" : "d4554e6c-67f1-47bc-a923-a94c7e38b01f",
      "username" : "kobeandjoran"
    },
    "ddf47021-8118-40dd-8a27-a214edb017fd" : {
      "age" : {
        "age" : 21,
        "day" : "7",
        "month" : "3",
        "year" : "1995"
      },
      "chat" : false,
      "chatlog" : false,
      "chatsearch" : false,
      "content" : {
        "games" : {
          "batmanarkhamknight" : {
            "chats" : 0,
            "intrest" : 0,
            "name" : "Batman Arkham Knight",
            "uid" : "085557-656-325-8b4-3d9b1c573"
          },
          "bloodborne" : {
            "chats" : 0,
            "intrest" : 0,
            "name" : "Blood Borne",
            "uid" : "541a54-037-a90-44f-c55353bf6"
          },
          "fallout4" : {
            "chats" : 0,
            "intrest" : 0,
            "name" : "Fallout 4",
            "uid" : "d7567e-46a-26e-537-8215e1735"
          },
          "watchdogs" : {
            "chats" : 0,
            "intrest" : 0,
            "name" : "Watch Dogs",
            "uid" : "96d33b-598-891-6ba-35212c097"
          }
        },
        "tv_shows" : {
          "americanhorrorstory" : {
            "chats" : 0,
            "intrest" : 0,
            "name" : "American Horror Story",
            "uid" : "b2ba4f-6f7-bed-aaa-59571eb75"
          },
          "arrow" : {
            "chats" : 0,
            "intrest" : 0,
            "name" : "Arrow",
            "uid" : "3ca510-df6-f9e-e24-a73b21ecd"
          },
          "bojackhorseman" : {
            "chats" : 0,
            "intrest" : 0,
            "name" : "Bojack Horseman",
            "uid" : "bcab14-ca1-18c-ea4-356496c3a"
          },
          "daredevil" : {
            "chats" : 0,
            "intrest" : 0,
            "name" : "Dare Devil",
            "uid" : "29fe21-d00-917-f43-d4e0cf5e9"
          },
          "gameofthrones" : {
            "chats" : 0,
            "intrest" : 0,
            "name" : "Game Of Thrones",
            "uid" : "e1d437-d00-117-ccc-210017dfa"
          },
          "houseofcards" : {
            "chats" : 0,
            "intrest" : 0,
            "name" : "House Of Cards",
            "uid" : "0f8612-0a0-73d-5e6-a0363eb34"
          },
          "narcos" : {
            "chats" : 0,
            "intrest" : 0,
            "name" : "Narcos",
            "uid" : "9a08bf-434-737-6ef-1e0e1dad1"
          },
          "orangeisthenewblack" : {
            "chats" : 0,
            "intrest" : 0,
            "name" : "Orange Is The New Black",
            "uid" : "1faf28-417-83f-765-ff3c21090"
          },
          "scream" : {
            "chats" : 0,
            "intrest" : 0,
            "name" : "Scream",
            "uid" : "87bc8c-f90-d85-c44-daf143df8"
          },
          "suits" : {
            "chats" : 0,
            "intrest" : 0,
            "name" : "Suits",
            "uid" : "ca953d-919-401-7e9-a2b44410f"
          },
          "supernatural" : {
            "chats" : 0,
            "intrest" : 0,
            "name" : "Super Natural",
            "uid" : "7291d0-645-9f4-446-d2464973e"
          },
          "thewalkingdead" : {
            "chats" : 0,
            "intrest" : 0,
            "name" : "The Walking Dead",
            "uid" : "0cb6a4-5e5-b63-f4e-c7fb3b75f"
          },
          "truedetective" : {
            "chats" : 0,
            "intrest" : 0,
            "name" : "True Detective",
            "uid" : "749767-585-561-5fb-64b93cda3"
          }
        }
      },
      "date" : "14/1/2016 ( 15:8:20:445 ) ",
      "email" : "lowry@gmail.com",
      "facebook_auth" : false,
      "google_auth" : false,
      "ip_address" : "70.27.105.227",
      "logged_in" : true,
      "name" : "jaden banson",
      "onefan_auth" : true,
      "password" : "1234",
      "personal_look" : false,
      "udid" : "ddf47021-8118-40dd-8a27-a214edb017fd",
      "username" : "lowry_nba"
    }
  }
}
